<annotation>
	<folder>Beauty-2</folder>
	<filename>1167_59_54226_68_2018-02-13T13-12-01-584Z.jpg</filename>
	<path>F:\hacker earth\annotation 28-05-18\akash\Beauty-2\1167_59_54226_68_2018-02-13T13-12-01-584Z.jpg</path>
	<source>
		<database>Unknown</database>
	</source>
	<size>
		<width>409</width>
		<height>728</height>
		<depth>3</depth>
	</size>
	<segmented>0</segmented>
	<object>
		<name>venus</name>
		<pose>Unspecified</pose>
		<truncated>0</truncated>
		<difficult>0</difficult>
		<bndbox>
			<xmin>276</xmin>
			<ymin>224</ymin>
			<xmax>319</xmax>
			<ymax>261</ymax>
		</bndbox>
	</object>
	<object>
		<name>venus</name>
		<pose>Unspecified</pose>
		<truncated>0</truncated>
		<difficult>0</difficult>
		<bndbox>
			<xmin>271</xmin>
			<ymin>203</ymin>
			<xmax>311</xmax>
			<ymax>222</ymax>
		</bndbox>
	</object>
	<object>
		<name>venus</name>
		<pose>Unspecified</pose>
		<truncated>0</truncated>
		<difficult>0</difficult>
		<bndbox>
			<xmin>224</xmin>
			<ymin>214</ymin>
			<xmax>264</xmax>
			<ymax>262</ymax>
		</bndbox>
	</object>
</annotation>
