<annotation>
	<folder>Beauty-2</folder>
	<filename>4324_59_82751_68_2018-02-26T11-45-04-659Z.jpg</filename>
	<path>F:\hacker earth\annotation 28-05-18\akash\Beauty-2\4324_59_82751_68_2018-02-26T11-45-04-659Z.jpg</path>
	<source>
		<database>Unknown</database>
	</source>
	<size>
		<width>409</width>
		<height>728</height>
		<depth>3</depth>
	</size>
	<segmented>0</segmented>
	<object>
		<name>venus</name>
		<pose>Unspecified</pose>
		<truncated>0</truncated>
		<difficult>0</difficult>
		<bndbox>
			<xmin>275</xmin>
			<ymin>83</ymin>
			<xmax>323</xmax>
			<ymax>119</ymax>
		</bndbox>
	</object>
	<object>
		<name>venus</name>
		<pose>Unspecified</pose>
		<truncated>0</truncated>
		<difficult>0</difficult>
		<bndbox>
			<xmin>243</xmin>
			<ymin>71</ymin>
			<xmax>275</xmax>
			<ymax>119</ymax>
		</bndbox>
	</object>
	<object>
		<name>venus</name>
		<pose>Unspecified</pose>
		<truncated>0</truncated>
		<difficult>0</difficult>
		<bndbox>
			<xmin>206</xmin>
			<ymin>71</ymin>
			<xmax>243</xmax>
			<ymax>117</ymax>
		</bndbox>
	</object>
</annotation>
