<annotation>
	<folder>Beauty-2</folder>
	<filename>4367_59_55001_68_2018-02-22T08-06-36-644Z.jpg</filename>
	<path>F:\hacker earth\annotation 28-05-18\akash\Beauty-2\4367_59_55001_68_2018-02-22T08-06-36-644Z.jpg</path>
	<source>
		<database>Unknown</database>
	</source>
	<size>
		<width>575</width>
		<height>1024</height>
		<depth>3</depth>
	</size>
	<segmented>0</segmented>
	<object>
		<name>venus</name>
		<pose>Unspecified</pose>
		<truncated>0</truncated>
		<difficult>0</difficult>
		<bndbox>
			<xmin>413</xmin>
			<ymin>160</ymin>
			<xmax>455</xmax>
			<ymax>246</ymax>
		</bndbox>
	</object>
	<object>
		<name>venus</name>
		<pose>Unspecified</pose>
		<truncated>0</truncated>
		<difficult>0</difficult>
		<bndbox>
			<xmin>380</xmin>
			<ymin>172</ymin>
			<xmax>413</xmax>
			<ymax>246</ymax>
		</bndbox>
	</object>
	<object>
		<name>venus</name>
		<pose>Unspecified</pose>
		<truncated>0</truncated>
		<difficult>0</difficult>
		<bndbox>
			<xmin>340</xmin>
			<ymin>172</ymin>
			<xmax>380</xmax>
			<ymax>249</ymax>
		</bndbox>
	</object>
	<object>
		<name>venus</name>
		<pose>Unspecified</pose>
		<truncated>0</truncated>
		<difficult>0</difficult>
		<bndbox>
			<xmin>309</xmin>
			<ymin>193</ymin>
			<xmax>340</xmax>
			<ymax>249</ymax>
		</bndbox>
	</object>
</annotation>
