<annotation>
	<folder>Beauty-2</folder>
	<filename>5022_59_225069_68_2018-02-03T02-42-35-615Z.jpg</filename>
	<path>F:\hacker earth\annotation 28-05-18\akash\Beauty-2\5022_59_225069_68_2018-02-03T02-42-35-615Z.jpg</path>
	<source>
		<database>Unknown</database>
	</source>
	<size>
		<width>409</width>
		<height>728</height>
		<depth>3</depth>
	</size>
	<segmented>0</segmented>
	<object>
		<name>venus</name>
		<pose>Unspecified</pose>
		<truncated>0</truncated>
		<difficult>0</difficult>
		<bndbox>
			<xmin>236</xmin>
			<ymin>235</ymin>
			<xmax>336</xmax>
			<ymax>283</ymax>
		</bndbox>
	</object>
</annotation>
