<annotation>
	<folder>venus</folder>
	<filename>2215_59_39481_69_2018-02-14T05-19-32-917Z.jpg</filename>
	<path>D:\Ashu\windows_v1.6.1\folder3\venus\2215_59_39481_69_2018-02-14T05-19-32-917Z.jpg</path>
	<source>
		<database>Unknown</database>
	</source>
	<size>
		<width>409</width>
		<height>728</height>
		<depth>3</depth>
	</size>
	<segmented>0</segmented>
	<object>
		<name>venus</name>
		<pose>Unspecified</pose>
		<truncated>0</truncated>
		<difficult>0</difficult>
		<bndbox>
			<xmin>124</xmin>
			<ymin>150</ymin>
			<xmax>246</xmax>
			<ymax>398</ymax>
		</bndbox>
	</object>
</annotation>
