<annotation>
	<folder>venus</folder>
	<filename>2454_57_22840_69_2018-02-08T11-22-20-763Z.jpg</filename>
	<path>D:\Ashu\windows_v1.6.1\folder3\venus\2454_57_22840_69_2018-02-08T11-22-20-763Z.jpg</path>
	<source>
		<database>Unknown</database>
	</source>
	<size>
		<width>409</width>
		<height>728</height>
		<depth>3</depth>
	</size>
	<segmented>0</segmented>
	<object>
		<name>venus</name>
		<pose>Unspecified</pose>
		<truncated>0</truncated>
		<difficult>0</difficult>
		<bndbox>
			<xmin>274</xmin>
			<ymin>158</ymin>
			<xmax>384</xmax>
			<ymax>353</ymax>
		</bndbox>
	</object>
	<object>
		<name>venus</name>
		<pose>Unspecified</pose>
		<truncated>0</truncated>
		<difficult>0</difficult>
		<bndbox>
			<xmin>269</xmin>
			<ymin>372</ymin>
			<xmax>381</xmax>
			<ymax>481</ymax>
		</bndbox>
	</object>
</annotation>
