<annotation>
	<folder>oralcare</folder>
	<filename>1267_58_158513_62_2018-02-05T03-44-11-472Z.jpg</filename>
	<path>/home/stallians/Desktop/folder3/oralcare/1267_58_158513_62_2018-02-05T03-44-11-472Z.jpg</path>
	<source>
		<database>Unknown</database>
	</source>
	<size>
		<width>409</width>
		<height>728</height>
		<depth>3</depth>
	</size>
	<segmented>0</segmented>
	<object>
		<name>oralb</name>
		<pose>Unspecified</pose>
		<truncated>0</truncated>
		<difficult>0</difficult>
		<bndbox>
			<xmin>127</xmin>
			<ymin>175</ymin>
			<xmax>279</xmax>
			<ymax>336</ymax>
		</bndbox>
	</object>
	<object>
		<name>oralb</name>
		<pose>Unspecified</pose>
		<truncated>0</truncated>
		<difficult>0</difficult>
		<bndbox>
			<xmin>107</xmin>
			<ymin>387</ymin>
			<xmax>288</xmax>
			<ymax>619</ymax>
		</bndbox>
	</object>
</annotation>
