<annotation>
	<folder>oralcare</folder>
	<filename>1904_57_43683_62_2018-02-02T12-57-18-284Z.jpg</filename>
	<path>E:\ML-DL\Hackerearth\folder3\oralcare\1904_57_43683_62_2018-02-02T12-57-18-284Z.jpg</path>
	<source>
		<database>Unknown</database>
	</source>
	<size>
		<width>409</width>
		<height>728</height>
		<depth>3</depth>
	</size>
	<segmented>0</segmented>
	<object>
		<name>oralb</name>
		<pose>Unspecified</pose>
		<truncated>0</truncated>
		<difficult>0</difficult>
		<bndbox>
			<xmin>188</xmin>
			<ymin>183</ymin>
			<xmax>256</xmax>
			<ymax>376</ymax>
		</bndbox>
	</object>
	<object>
		<name>oralb</name>
		<pose>Unspecified</pose>
		<truncated>0</truncated>
		<difficult>0</difficult>
		<bndbox>
			<xmin>258</xmin>
			<ymin>207</ymin>
			<xmax>330</xmax>
			<ymax>364</ymax>
		</bndbox>
	</object>
	<object>
		<name>oralb</name>
		<pose>Unspecified</pose>
		<truncated>0</truncated>
		<difficult>0</difficult>
		<bndbox>
			<xmin>161</xmin>
			<ymin>386</ymin>
			<xmax>224</xmax>
			<ymax>579</ymax>
		</bndbox>
	</object>
	<object>
		<name>oralb</name>
		<pose>Unspecified</pose>
		<truncated>0</truncated>
		<difficult>0</difficult>
		<bndbox>
			<xmin>226</xmin>
			<ymin>395</ymin>
			<xmax>271</xmax>
			<ymax>580</ymax>
		</bndbox>
	</object>
	<object>
		<name>oralb</name>
		<pose>Unspecified</pose>
		<truncated>0</truncated>
		<difficult>0</difficult>
		<bndbox>
			<xmin>271</xmin>
			<ymin>396</ymin>
			<xmax>335</xmax>
			<ymax>567</ymax>
		</bndbox>
	</object>
</annotation>
