<annotation>
	<folder>oralcare</folder>
	<filename>2342_56_54059_62_2018-02-05T11-42-39-316Z.jpg</filename>
	<path>E:\ML-DL\Hackerearth\folder3\oralcare\2342_56_54059_62_2018-02-05T11-42-39-316Z.jpg</path>
	<source>
		<database>Unknown</database>
	</source>
	<size>
		<width>546</width>
		<height>728</height>
		<depth>3</depth>
	</size>
	<segmented>0</segmented>
	<object>
		<name>pharmacy</name>
		<pose>Unspecified</pose>
		<truncated>0</truncated>
		<difficult>0</difficult>
		<bndbox>
			<xmin>226</xmin>
			<ymin>206</ymin>
			<xmax>390</xmax>
			<ymax>292</ymax>
		</bndbox>
	</object>
	<object>
		<name>pharmacy</name>
		<pose>Unspecified</pose>
		<truncated>0</truncated>
		<difficult>0</difficult>
		<bndbox>
			<xmin>225</xmin>
			<ymin>395</ymin>
			<xmax>264</xmax>
			<ymax>641</ymax>
		</bndbox>
	</object>
	<object>
		<name>pharmacy</name>
		<pose>Unspecified</pose>
		<truncated>0</truncated>
		<difficult>0</difficult>
		<bndbox>
			<xmin>271</xmin>
			<ymin>408</ymin>
			<xmax>317</xmax>
			<ymax>650</ymax>
		</bndbox>
	</object>
	<object>
		<name>pharmacy</name>
		<pose>Unspecified</pose>
		<truncated>0</truncated>
		<difficult>0</difficult>
		<bndbox>
			<xmin>324</xmin>
			<ymin>411</ymin>
			<xmax>380</xmax>
			<ymax>657</ymax>
		</bndbox>
	</object>
</annotation>
