<annotation>
	<folder>oralcare</folder>
	<filename>4309_28940_57129_62_2018-02-02T07-56-06-273Z.jpg</filename>
	<path>H:\windows_v1.6.1\oralcare\4309_28940_57129_62_2018-02-02T07-56-06-273Z.jpg</path>
	<source>
		<database>Unknown</database>
	</source>
	<size>
		<width>546</width>
		<height>728</height>
		<depth>3</depth>
	</size>
	<segmented>0</segmented>
	<object>
		<name>oralb</name>
		<pose>Unspecified</pose>
		<truncated>0</truncated>
		<difficult>0</difficult>
		<bndbox>
			<xmin>246</xmin>
			<ymin>175</ymin>
			<xmax>289</xmax>
			<ymax>301</ymax>
		</bndbox>
	</object>
	<object>
		<name>oralb</name>
		<pose>Unspecified</pose>
		<truncated>0</truncated>
		<difficult>0</difficult>
		<bndbox>
			<xmin>300</xmin>
			<ymin>177</ymin>
			<xmax>329</xmax>
			<ymax>296</ymax>
		</bndbox>
	</object>
	<object>
		<name>oralb</name>
		<pose>Unspecified</pose>
		<truncated>0</truncated>
		<difficult>0</difficult>
		<bndbox>
			<xmin>251</xmin>
			<ymin>326</ymin>
			<xmax>275</xmax>
			<ymax>444</ymax>
		</bndbox>
	</object>
	<object>
		<name>oralb</name>
		<pose>Unspecified</pose>
		<truncated>0</truncated>
		<difficult>0</difficult>
		<bndbox>
			<xmin>289</xmin>
			<ymin>332</ymin>
			<xmax>317</xmax>
			<ymax>445</ymax>
		</bndbox>
	</object>
</annotation>
