<annotation>
	<folder>temp_test - Copy</folder>
	<filename>5831_59_102839_62_2018-02-05T07-58-57-914Z.jpg</filename>
	<path>E:\ML-DL\Hackerearth\temp_test - Copy\5831_59_102839_62_2018-02-05T07-58-57-914Z.jpg</path>
	<source>
		<database>Unknown</database>
	</source>
	<size>
		<width>409</width>
		<height>728</height>
		<depth>3</depth>
	</size>
	<segmented>0</segmented>
	<object>
		<name>pharmacy</name>
		<pose>Unspecified</pose>
		<truncated>0</truncated>
		<difficult>0</difficult>
		<bndbox>
			<xmin>94</xmin>
			<ymin>111</ymin>
			<xmax>158</xmax>
			<ymax>389</ymax>
		</bndbox>
	</object>
	<object>
		<name>pharmacy</name>
		<pose>Unspecified</pose>
		<truncated>0</truncated>
		<difficult>0</difficult>
		<bndbox>
			<xmin>158</xmin>
			<ymin>121</ymin>
			<xmax>211</xmax>
			<ymax>391</ymax>
		</bndbox>
	</object>
	<object>
		<name>pharmacy</name>
		<pose>Unspecified</pose>
		<truncated>0</truncated>
		<difficult>0</difficult>
		<bndbox>
			<xmin>214</xmin>
			<ymin>125</ymin>
			<xmax>256</xmax>
			<ymax>389</ymax>
		</bndbox>
	</object>
	<object>
		<name>pharmacy</name>
		<pose>Unspecified</pose>
		<truncated>0</truncated>
		<difficult>0</difficult>
		<bndbox>
			<xmin>224</xmin>
			<ymin>435</ymin>
			<xmax>259</xmax>
			<ymax>653</ymax>
		</bndbox>
	</object>
	<object>
		<name>pharmacy</name>
		<pose>Unspecified</pose>
		<truncated>0</truncated>
		<difficult>0</difficult>
		<bndbox>
			<xmin>168</xmin>
			<ymin>431</ymin>
			<xmax>205</xmax>
			<ymax>665</ymax>
		</bndbox>
	</object>
	<object>
		<name>pharmacy</name>
		<pose>Unspecified</pose>
		<truncated>0</truncated>
		<difficult>0</difficult>
		<bndbox>
			<xmin>112</xmin>
			<ymin>437</ymin>
			<xmax>154</xmax>
			<ymax>665</ymax>
		</bndbox>
	</object>
	<object>
		<name>pharmacy</name>
		<pose>Unspecified</pose>
		<truncated>0</truncated>
		<difficult>0</difficult>
		<bndbox>
			<xmin>52</xmin>
			<ymin>477</ymin>
			<xmax>114</xmax>
			<ymax>556</ymax>
		</bndbox>
	</object>
</annotation>
