<annotation>
	<folder>temp_test - Copy</folder>
	<filename>6065_56_90940_62_2018-02-04T02-43-17-823Z.jpg</filename>
	<path>E:\ML-DL\Hackerearth\temp_test - Copy\6065_56_90940_62_2018-02-04T02-43-17-823Z.jpg</path>
	<source>
		<database>Unknown</database>
	</source>
	<size>
		<width>728</width>
		<height>546</height>
		<depth>3</depth>
	</size>
	<segmented>0</segmented>
	<object>
		<name>oralb</name>
		<pose>Unspecified</pose>
		<truncated>0</truncated>
		<difficult>0</difficult>
		<bndbox>
			<xmin>136</xmin>
			<ymin>161</ymin>
			<xmax>436</xmax>
			<ymax>207</ymax>
		</bndbox>
	</object>
	<object>
		<name>oralb</name>
		<pose>Unspecified</pose>
		<truncated>0</truncated>
		<difficult>0</difficult>
		<bndbox>
			<xmin>132</xmin>
			<ymin>231</ymin>
			<xmax>434</xmax>
			<ymax>274</ymax>
		</bndbox>
	</object>
	<object>
		<name>oralb</name>
		<pose>Unspecified</pose>
		<truncated>0</truncated>
		<difficult>0</difficult>
		<bndbox>
			<xmin>145</xmin>
			<ymin>278</ymin>
			<xmax>431</xmax>
			<ymax>326</ymax>
		</bndbox>
	</object>
	<object>
		<name>oralb</name>
		<pose>Unspecified</pose>
		<truncated>0</truncated>
		<difficult>0</difficult>
		<bndbox>
			<xmin>505</xmin>
			<ymin>123</ymin>
			<xmax>714</xmax>
			<ymax>214</ymax>
		</bndbox>
	</object>
	<object>
		<name>oralb</name>
		<pose>Unspecified</pose>
		<truncated>0</truncated>
		<difficult>0</difficult>
		<bndbox>
			<xmin>496</xmin>
			<ymin>176</ymin>
			<xmax>702</xmax>
			<ymax>266</ymax>
		</bndbox>
	</object>
	<object>
		<name>oralb</name>
		<pose>Unspecified</pose>
		<truncated>0</truncated>
		<difficult>0</difficult>
		<bndbox>
			<xmin>489</xmin>
			<ymin>261</ymin>
			<xmax>693</xmax>
			<ymax>300</ymax>
		</bndbox>
	</object>
</annotation>
