<annotation>
	<folder>Beauty</folder>
	<filename>4060_61_213131_68_2018-04-10T12-29-38-129Z.jpg</filename>
	<path>C:\Users\Mundhare\Desktop\hacker earth\annotation 28-05-18\akash\Beauty\4060_61_213131_68_2018-04-10T12-29-38-129Z.jpg</path>
	<source>
		<database>Unknown</database>
	</source>
	<size>
		<width>409</width>
		<height>728</height>
		<depth>3</depth>
	</size>
	<segmented>0</segmented>
	<object>
		<name>venus</name>
		<pose>Unspecified</pose>
		<truncated>0</truncated>
		<difficult>0</difficult>
		<bndbox>
			<xmin>301</xmin>
			<ymin>23</ymin>
			<xmax>330</xmax>
			<ymax>79</ymax>
		</bndbox>
	</object>
	<object>
		<name>venus</name>
		<pose>Unspecified</pose>
		<truncated>0</truncated>
		<difficult>0</difficult>
		<bndbox>
			<xmin>277</xmin>
			<ymin>21</ymin>
			<xmax>301</xmax>
			<ymax>79</ymax>
		</bndbox>
	</object>
</annotation>
