<annotation>
	<folder>Beauty</folder>
	<filename>4321_61_154331_68_2018-04-12T12-07-47-198Z.jpg</filename>
	<path>C:\Users\Mundhare\Desktop\hacker earth\annotation 28-05-18\akash\Beauty\4321_61_154331_68_2018-04-12T12-07-47-198Z.jpg</path>
	<source>
		<database>Unknown</database>
	</source>
	<size>
		<width>409</width>
		<height>728</height>
		<depth>3</depth>
	</size>
	<segmented>0</segmented>
	<object>
		<name>venus</name>
		<pose>Unspecified</pose>
		<truncated>0</truncated>
		<difficult>0</difficult>
		<bndbox>
			<xmin>98</xmin>
			<ymin>240</ymin>
			<xmax>120</xmax>
			<ymax>294</ymax>
		</bndbox>
	</object>
	<object>
		<name>venus</name>
		<pose>Unspecified</pose>
		<truncated>0</truncated>
		<difficult>0</difficult>
		<bndbox>
			<xmin>124</xmin>
			<ymin>241</ymin>
			<xmax>143</xmax>
			<ymax>293</ymax>
		</bndbox>
	</object>
	<object>
		<name>venus</name>
		<pose>Unspecified</pose>
		<truncated>0</truncated>
		<difficult>0</difficult>
		<bndbox>
			<xmin>147</xmin>
			<ymin>243</ymin>
			<xmax>165</xmax>
			<ymax>298</ymax>
		</bndbox>
	</object>
	<object>
		<name>gillete</name>
		<pose>Unspecified</pose>
		<truncated>0</truncated>
		<difficult>0</difficult>
		<bndbox>
			<xmin>325</xmin>
			<ymin>90</ymin>
			<xmax>355</xmax>
			<ymax>118</ymax>
		</bndbox>
	</object>
</annotation>
