<annotation>
	<folder>Beauty</folder>
	<filename>7111_61_62732_68_2018-04-09T11-29-45-633Z.jpg</filename>
	<path>C:\Users\Mundhare\Desktop\hacker earth\annotation 28-05-18\akash\Beauty\7111_61_62732_68_2018-04-09T11-29-45-633Z.jpg</path>
	<source>
		<database>Unknown</database>
	</source>
	<size>
		<width>728</width>
		<height>409</height>
		<depth>3</depth>
	</size>
	<segmented>0</segmented>
	<object>
		<name>venus</name>
		<pose>Unspecified</pose>
		<truncated>0</truncated>
		<difficult>0</difficult>
		<bndbox>
			<xmin>181</xmin>
			<ymin>55</ymin>
			<xmax>242</xmax>
			<ymax>126</ymax>
		</bndbox>
	</object>
	<object>
		<name>venus</name>
		<pose>Unspecified</pose>
		<truncated>0</truncated>
		<difficult>0</difficult>
		<bndbox>
			<xmin>71</xmin>
			<ymin>55</ymin>
			<xmax>133</xmax>
			<ymax>118</ymax>
		</bndbox>
	</object>
</annotation>
